classvalidator/__init__.py
classvalidator/validator.py
classvalidator-0.0.1.dist-info/LICENSE
classvalidator-0.0.1.dist-info/METADATA
classvalidator-0.0.1.dist-info/WHEEL
classvalidator-0.0.1.dist-info/top_level.txt
classvalidator-0.0.1.dist-info/RECORD
