Metadata-Version: 2.1
Name: classvalidator
Version: 0.0.1
Summary: Runtime type validation of Dataclass instances
Home-page: http://github.com/ifedapoolarewaju/classvalidator/
Author: Ifedapo Olarewaju
Author-email: ifedapoolarewaju@gmail.com
License: MIT
Platform: any
Classifier: Programming Language :: Python :: 3
Classifier: Natural Language :: English
Classifier: Intended Audience :: Developers
Classifier: License :: OSI Approved :: MIT License
Classifier: Operating System :: OS Independent
Classifier: Topic :: Software Development :: Libraries :: Python Modules
Requires-Dist: typing-inspect (==0.6.0)
